rough_notation/__init__.py
rough_notation/frontend/build/asset-manifest.json
rough_notation/frontend/build/bootstrap.min.css
rough_notation/frontend/build/index.html
rough_notation/frontend/build/precache-manifest.0b222b73d55888e33f69c285ccc315e1.js
rough_notation/frontend/build/service-worker.js
rough_notation/frontend/build/static/js/2.5280e3f5.chunk.js
rough_notation/frontend/build/static/js/2.5280e3f5.chunk.js.LICENSE.txt
rough_notation/frontend/build/static/js/2.5280e3f5.chunk.js.map
rough_notation/frontend/build/static/js/main.f894e524.chunk.js
rough_notation/frontend/build/static/js/main.f894e524.chunk.js.map
rough_notation/frontend/build/static/js/runtime-main.44d30fc2.js
rough_notation/frontend/build/static/js/runtime-main.44d30fc2.js.map
rough_notation-0.0.1.dist-info/LICENSE
rough_notation-0.0.1.dist-info/METADATA
rough_notation-0.0.1.dist-info/WHEEL
rough_notation-0.0.1.dist-info/top_level.txt
rough_notation-0.0.1.dist-info/RECORD
